Workbook

Sheet Start Here
B1: Pressure Washing Quote Calculator (Free Demo)
B2: FREE DEMO by LaneLedger Co. · Microsoft Excel and Google Sheets
B4: Build a pressure washing quote and see your real job cost and profit before you send the price.
B6: What this free demo includes
B7: • Quote Calculator with customer price, travel fee, discount, tax, deposit and a copy-ready quote message
B8: • Your internal cost & profit: labor, chemicals, fuel, equipment, margin and effective hourly rate
B9: • Price Setup for up to 5 services, plus Settings
B11: The full version adds
B12: • Up to 30 services in Price Setup
B13: • Jobs Log: pipeline from Quoted to Paid, lead sources and profit per job (500 rows)
B14: • Clients CRM with total spent, last service and automatic re-wash reminders
B15: • Expenses tracker and a yearly Dashboard with monthly profit, win rate and unpaid jobs
... B22: This demo is free to use in your own business. Please don't resell it.

Sheet Quote Calculator
A1: Quote Calculator
A2: Pick services, enter quantities. Customer price on the left, your real cost and profit on the right. | G2: Free demo · Get the full toolkit on Etsy →
A4: Job details | G4: Your cost & profit (internal)
A5: Client name | B5: Example: J. Smith | G5: Not shown to the customer
A6: Job address | B6: 12 Oak Street | G6: Estimated work time (hours) | H6: =(IF(A11="",0,N(B11)/100*IFERROR(INDEX('Price Setup'!$F$5:$F$34,MATCH(A11,'Price Setup'!$A$5:$A$34,0)),0))+IF(A12="",0,N(B12)/100*IFERROR(INDEX('Price Setup'!$F$5:$F$34,MATCH(A12,'Price Setup'!$A$5:$A$34,0)),0))+IF(A13="",0,N(B13)/100*IFERROR(INDEX('Price Setup'!$F$5:$F$34,MATCH(A13,'Price Setup'!$A$5:$A$34,0)),0))+IF(A14="",0,N(B14)/100*IFERROR(INDEX('Price Setup'!$F$5:$F$34,MATCH(A14,'Price Setup'!$A$5:$A$34,0)),0))+IF(A15="",0,N(B15)/100*IFERROR(INDEX('Price Setup'!$F$5:$F$34,MATCH(A15,'Price Setup'!$A$5:$A$34,0)),0))+IF(A16="",0,N(B16)/100*IFERROR(INDEX('Price Setup'!$F$5:$F$34,MATCH(A16,'Price Setup'!$A$5:$A$34,0)),0))+IF(A17="",0,N(B17)/100*IFERROR(INDEX('Price Setup'!$F$5:$F$34,MATCH(A17,'Price Setup'!$A$5:$A$34,0)),0))+IF(A18="",0,N(B18)/100*IFERROR(INDEX('Price Setup'!$F$5:$F$34,MATCH(A18,'Price Setup'!$A$5:$A$34,0)),0))+IF(A19="",0,N(B19)/100*IFERROR(INDEX('Price Setup'!$F$5:$F$34,MATCH(A19,'Price Setup'!$A$5:$A$34,0)),0))+IF(A20="",0,N(B20)/100*IFERROR(INDEX('Price Setup'!$F$5:$F$34,MATCH(A20,'Price Setup'!$A$5:$A$34,0)),0)))/60 -> 2.3333333
A7: Quote date | B7: 46319 | G7: Labor cost | H7: =H6*Settings!$B$9 -> 81.666667
A8: Distance from base (miles or km, one way) | B8: 22 | G8: Chemical cost | H8: =IF(A11="",0,N(B11)*IFERROR(INDEX('Price Setup'!$E$5:$E$34,MATCH(A11,'Price Setup'!$A$5:$A$34,0)),0))+IF(A12="",0,N(B12)*IFERROR(INDEX('Price Setup'!$E$5:$E$34,MATCH(A12,'Price Setup'!$A$5:$A$34,0)),0))+IF(A13="",0,N(B13)*IFERROR(INDEX('Price Setup'!$E$5:$E$34,MATCH(A13,'Price Setup'!$A$5:$A$34,0)),0))+IF(A14="",0,N(B14)*IFERROR(INDEX('Price Setup'!$E$5:$E$34,MATCH(A14,'Price Setup'!$A$5:$A$34,0)),0))+IF(A15="",0,N(B15)*IFERROR(INDEX('Price Setup'!$E$5:$E$34,MATCH(A15,'Price Setup'!$A$5:$A$34,0)),0))+IF(A16="",0,N(B16)*IFERROR(INDEX('Price Setup'!$E$5:$E$34,MATCH(A16,'Price Setup'!$A$5:$A$34,0)),0))+IF(A17="",0,N(B17)*IFERROR(INDEX('Price Setup'!$E$5:$E$34,MATCH(A17,'Price Setup'!$A$5:$A$34,0)),0))+IF(A18="",0,N(B18)*IFERROR(INDEX('Price Setup'!$E$5:$E$34,MATCH(A18,'Price Setup'!$A$5:$A$34,0)),0))+IF(A19="",0,N(B19)*IFERROR(INDEX('Price Setup'!$E$5:$E$34,MATCH(A19,'Price Setup'!$A$5:$A$34,0)),0))+IF(A20="",0,N(B20)*IFERROR(INDEX('Price Setup'!$E$5:$E$34,MATCH(A20,'Price Setup'!$A$5:$A$34,0)),0)) -> 64.8
G9: Fuel & vehicle (round trip) | H9: =B8*2*Settings!$B$10 -> 30.8
A10: Service | B10: Quantity | C10: Unit | D10: Price / Unit | E10: Line Total | G10: Equipment wear | H10: =H6*Settings!$B$11 -> 9.3333333
A11: Driveway / concrete | B11: 1200 | C11: =IF(A11="","",IFERROR(INDEX('Price Setup'!$B$5:$B$34,MATCH(A11,'Price Setup'!$A$5:$A$34,0)),"?")) -> sq ft | D11: =IF(A11="","",IFERROR(INDEX('Price Setup'!$C$5:$C$34,MATCH(A11,'Price Setup'!$A$5:$A$34,0)),0)) -> 0.18 | E11: =IF(A11="","",MAX(N(B11)*D11,IFERROR(INDEX('Price Setup'!$D$5:$D$34,MATCH(A11,'Price Setup'!$A$5:$A$34,0)),0))) -> 216 | G11: Total job cost | H11: =SUM(H7:H10) -> 186.6
A12: House wash (soft wash) | B12: 2400 | C12: =IF(A12="","",IFERROR(INDEX('Price Setup'!$B$5:$B$34,MATCH(A12,'Price Setup'!$A$5:$A$34,0)),"?")) -> sq ft | D12: =IF(A12="","",IFERROR(INDEX('Price Setup'!$C$5:$C$34,MATCH(A12,'Price Setup'!$A$5:$A$34,0)),0)) -> 0.22 | E12: =IF(A12="","",MAX(N(B12)*D12,IFERROR(INDEX('Price Setup'!$D$5:$D$34,MATCH(A12,'Price Setup'!$A$5:$A$34,0)),0))) -> 528 | G12: Revenue before tax | H12: =E22+E24+E25 -> 854.5
A13: Patio / pavers | B13: 400 | C13: =IF(A13="","",IFERROR(INDEX('Price Setup'!$B$5:$B$34,MATCH(A13,'Price Setup'!$A$5:$A$34,0)),"?")) -> sq ft | D13: =IF(A13="","",IFERROR(INDEX('Price Setup'!$C$5:$C$34,MATCH(A13,'Price Setup'!$A$5:$A$34,0)),0)) -> 0.25 | E13: =IF(A13="","",MAX(N(B13)*D13,IFERROR(INDEX('Price Setup'!$D$5:$D$34,MATCH(A13,'Price Setup'!$A$5:$A$34,0)),0))) -> 100 | G13: ESTIMATED PROFIT | H13: =H12-H11 -> 667.9
C14: =IF(A14="","",IFERROR(INDEX('Price Setup'!$B$5:$B$34,MATCH(A14,'Price Setup'!$A$5:$A$34,0)),"?")) | D14: =IF(A14="","",IFERROR(INDEX('Price Setup'!$C$5:$C$34,MATCH(A14,'Price Setup'!$A$5:$A$34,0)),0)) | E14: =IF(A14="","",MAX(N(B14)*D14,IFERROR(INDEX('Price Setup'!$D$5:$D$34,MATCH(A14,'Price Setup'!$A$5:$A$34,0)),0))) | G14: Profit margin | H14: =IF(H12=0,0,H13/H12) -> 0.78162668
C15: =IF(A15="","",IFERROR(INDEX('Price Setup'!$B$5:$B$34,MATCH(A15,'Price Setup'!$A$5:$A$34,0)),"?")) | D15: =IF(A15="","",IFERROR(INDEX('Price Setup'!$C$5:$C$34,MATCH(A15,'Price Setup'!$A$5:$A$34,0)),0)) | E15: =IF(A15="","",MAX(N(B15)*D15,IFERROR(INDEX('Price Setup'!$D$5:$D$34,MATCH(A15,'Price Setup'!$A$5:$A$34,0)),0))) | G15: Effective hourly rate | H15: =IF(H6=0,0,H13/H6+Settings!$B$9) -> 321.24286
C16: =IF(A16="","",IFERROR(INDEX('Price Setup'!$B$5:$B$34,MATCH(A16,'Price Setup'!$A$5:$A$34,0)),"?")) | D16: =IF(A16="","",IFERROR(INDEX('Price Setup'!$C$5:$C$34,MATCH(A16,'Price Setup'!$A$5:$A$34,0)),0)) | E16: =IF(A16="","",MAX(N(B16)*D16,IFERROR(INDEX('Price Setup'!$D$5:$D$34,MATCH(A16,'Price Setup'!$A$5:$A$34,0)),0))) | G16: Target margin (Settings) | H16: =Settings!$B$18 -> 0.4
C17: =IF(A17="","",IFERROR(INDEX('Price Setup'!$B$5:$B$34,MATCH(A17,'Price Setup'!$A$5:$A$34,0)),"?")) | D17: =IF(A17="","",IFERROR(INDEX('Price Setup'!$C$5:$C$34,MATCH(A17,'Price Setup'!$A$5:$A$34,0)),0)) | E17: =IF(A17="","",MAX(N(B17)*D17,IFERROR(INDEX('Price Setup'!$D$5:$D$34,MATCH(A17,'Price Setup'!$A$5:$A$34,0)),0))) | G17: Price needed for target margin | H17: =IF(1-H16<=0,"Lower target",H11/(1-H16)) -> 311
C18: =IF(A18="","",IFERROR(INDEX('Price Setup'!$B$5:$B$34,MATCH(A18,'Price Setup'!$A$5:$A$34,0)),"?")) | D18: =IF(A18="","",IFERROR(INDEX('Price Setup'!$C$5:$C$34,MATCH(A18,'Price Setup'!$A$5:$A$34,0)),0)) | E18: =IF(A18="","",MAX(N(B18)*D18,IFERROR(INDEX('Price Setup'!$D$5:$D$34,MATCH(A18,'Price Setup'!$A$5:$A$34,0)),0)))
C19: =IF(A19="","",IFERROR(INDEX('Price Setup'!$B$5:$B$34,MATCH(A19,'Price Setup'!$A$5:$A$34,0)),"?")) | D19: =IF(A19="","",IFERROR(INDEX('Price Setup'!$C$5:$C$34,MATCH(A19,'Price Setup'!$A$5:$A$34,0)),0)) | E19: =IF(A19="","",MAX(N(B19)*D19,IFERROR(INDEX('Price Setup'!$D$5:$D$34,MATCH(A19,'Price Setup'!$A$5:$A$34,0)),0))) | G19: =IF(H13<0,"⚠ This quote loses money. Raise prices or minimums.",IF(H14<H16,"⚠ Margin is below your target.","✓ Quote meets your target margin.")) -> ✓ Quote meets your target margin.
C20: =IF(A20="","",IFERROR(INDEX('Price Setup'!$B$5:$B$34,MATCH(A20,'Price Setup'!$A$5:$A$34,0)),"?")) | D20: =IF(A20="","",IFERROR(INDEX('Price Setup'!$C$5:$C$34,MATCH(A20,'Price Setup'!$A$5:$A$34,0)),0)) | E20: =IF(A20="","",MAX(N(B20)*D20,IFERROR(INDEX('Price Setup'!$D$5:$D$34,MATCH(A20,'Price Setup'!$A$5:$A$34,0)),0)))
A22: Services subtotal | E22: =SUM(E11:E20) -> 844
A23: Discount (%) | E23: 0
A24: Discount amount | E24: =-E22*E23 -> 0
A25: Travel fee | E25: =MAX(0,B8-Settings!$B$14)*Settings!$B$15 -> 10.5
A26: Tax | E26: =(E22+E24+E25)*Settings!$B$16 -> 0
A27: QUOTE TOTAL | E27: =E22+E24+E25+E26 -> 854.5
A28: Deposit due | E28: =E27*Settings!$B$17 -> 213.625
A29: Balance on completion | E29: =E27-E28 -> 640.875
A31: Copy-ready quote message
A32: ="Hi "&B5&", thank you for the opportunity! Your quote for "&B6&" is "&TEXT(E27,"#,##0.00")&". A deposit of "&TEXT(E28,"#,##0.00")&" confirms your booking. This quote includes: "&IF(A11="","",A11)&IF(A12="","",", "&A12)&IF(A13="","",", "&A13)&IF(A14="","",", "&A14)&IF(A15="","",", "&A15)&IF(COUNTA(A16:A20)>0," and more","")&". Questions? Contact "&Settings!$B$5&" at "&Settings!$B$6&"." -> Hi Example: J. Smith, thank you for the opportunity! Your quote for 12 Oak Street is 854.50. A deposit of 213.63 confirms your booking. This quote includes: Driveway / concrete, House wash (soft wash), Patio / pavers. Questions? Contact Your Business Name at you@example.com.

Sheet Price Setup
A1: Price Setup
A2: Your services and rates. EXAMPLE RATES - replace with your own local prices.
A4: Service | B4: Unit | C4: Price per Unit | D4: Minimum Charge | E4: Chemical Cost per Unit | F4: Minutes per 100 Units | H4: How this works
A5: Driveway / concrete | B5: sq ft | C5: 0.18 | D5: 99 | E5: 0.01 | F5: 4 | H5: • Line price = quantity x price per unit, but never below the minimum charge.
A6: House wash (soft wash) | B6: sq ft | C6: 0.22 | D6: 199 | E6: 0.02 | F6: 3 | H6: • Chemical cost per unit: what your chemicals cost per sq ft (or unit) cleaned.
A7: Roof soft wash | B7: sq ft | C7: 0.35 | D7: 349 | E7: 0.03 | F7: 4 | H7: • Minutes per 100 units: how long 100 sq ft (or units) takes your crew.
A8: Deck cleaning | B8: sq ft | C8: 0.4 | D8: 149 | E8: 0.02 | F8: 6 | H8: Example: 4 min per 100 sq ft means a 1,000 sq ft driveway takes about 40 minutes.
A9: Patio / pavers | B9: sq ft | C9: 0.25 | D9: 99 | E9: 0.012 | F9: 5 | H9: • For flat-rate services use unit 'job', price = your flat price, quantity = 1.
A10: Full version: up to 30 services → | H10: • Add up to 30 services. They appear in the Quote Calculator dropdown.

Sheet Settings
A1: Settings
A2: Your business numbers. Every other tab reads from here.
A4: Business | D4: Expense categories | F4: Lead sources
A5: Business name | B5: Your Business Name | D5: Chemicals & Detergents | F5: Google
A6: Phone / email for quotes | B6: you@example.com | D6: Fuel | F6: Facebook
D7: Equipment | F7: Nextdoor
A8: Costs | D8: Repairs & Maintenance | F8: Referral
A9: Labor cost per crew hour (wages + your time) | B9: 35 | D9: Insurance | F9: Door hanger / Flyer
A10: Fuel & vehicle cost per mile (or km) | B10: 0.7 | D10: Marketing & Ads | F10: Repeat client
A11: Equipment wear per job hour | B11: 4 | D11: Software & Phone | F11: Other
D12: Vehicle
A13: Pricing | D13: Licenses & Fees
A14: Free travel radius (miles or km) | B14: 15 | D14: Other
A15: Travel fee per mile beyond the radius | B15: 1.5
A16: Sales tax / VAT (%) | B16: 0
A17: Deposit required (%) | B17: 0.25 | D17: Job statuses (fixed)
A18: Target profit margin | B18: 0.4 | D18: Quoted
A19: Months until a client is due for a re-wash | B19: 12 | D19: Booked
D20: Done
D21: Paid
D22: Lost
